antipasta/__init__.py
antipasta/__version__.py
antipasta/py.typed
antipasta/cli/__init__.py
antipasta/cli/main.py
antipasta/cli/validation_utils.py
antipasta/cli/config/__init__.py
antipasta/cli/config/config_validate.py
antipasta/cli/config/config_generate/__init__.py
antipasta/cli/config/config_generate/file_operations.py
antipasta/cli/config/config_generate/interactive_prompts.py
antipasta/cli/config/config_generate/language_config.py
antipasta/cli/config/config_generate/main.py
antipasta/cli/config/config_generate/project_config.py
antipasta/cli/config/config_generate/validation.py
antipasta/cli/config/config_view/__init__.py
antipasta/cli/config/config_view/display_formats.py
antipasta/cli/config/config_view/main.py
antipasta/cli/config/config_view/table_display.py
antipasta/cli/metrics/__init__.py
antipasta/cli/metrics/metrics.py
antipasta/cli/metrics/metrics_utils_analysis.py
antipasta/cli/metrics/metrics_utils_collection.py
antipasta/cli/metrics/metrics_utils_config.py
antipasta/cli/metrics/metrics_utils_output.py
antipasta/cli/metrics/metrics_utils_override.py
antipasta/cli/stats/__init__.py
antipasta/cli/stats/command.py
antipasta/cli/stats/config.py
antipasta/cli/stats/utils.py
antipasta/cli/stats/aggregation/__init__.py
antipasta/cli/stats/aggregation/directory.py
antipasta/cli/stats/aggregation/module.py
antipasta/cli/stats/collection/__init__.py
antipasta/cli/stats/collection/analysis.py
antipasta/cli/stats/collection/file_collection.py
antipasta/cli/stats/collection/metrics.py
antipasta/cli/stats/output/__init__.py
antipasta/cli/stats/output/display.py
antipasta/core/__init__.py
antipasta/core/aggregator.py
antipasta/core/config.py
antipasta/core/config_override.py
antipasta/core/detector.py
antipasta/core/metric_models.py
antipasta/core/metrics.py
antipasta/core/violations.py
antipasta/hooks/__init__.py
antipasta/runners/__init__.py
antipasta/runners/base.py
antipasta/runners/javascript/__init__.py
antipasta/runners/python/__init__.py
antipasta-1.1.0.dist-info/METADATA
antipasta-1.1.0.dist-info/WHEEL
antipasta-1.1.0.dist-info/entry_points.txt
antipasta-1.1.0.dist-info/licenses/LICENSE
antipasta-1.1.0.dist-info/RECORD
