Metadata-Version: 2.4
Name: antipasta
Version: 1.1.0
Summary: A code quality monitoring and enforcement tool that analyzes a variety of code complexity metrics
Project-URL: Homepage, https://github.com/hesreallyhim/antipasta
Project-URL: Issues, https://github.com/hesreallyhim/antipasta/issues
Author-email: Really Him <hesreallyhim@proton.me>
License: MIT License
License-File: LICENSE
Keywords: code-quality,complexity,linting,metrics,static-analysis
Classifier: Development Status :: 5 - Production/Stable
Classifier: Intended Audience :: Developers
Classifier: License :: OSI Approved :: MIT License
Classifier: Programming Language :: Python :: 3
Classifier: Programming Language :: Python :: 3.11
Classifier: Programming Language :: Python :: 3.12
Classifier: Topic :: Software Development :: Quality Assurance
Classifier: Topic :: Software Development :: Testing
Requires-Python: >=3.11
Requires-Dist: click>=8.1.0
Requires-Dist: complexipy>=3.3.0
Requires-Dist: pathspec>=0.12.0
Requires-Dist: pydantic>=2.5.0
Requires-Dist: pyyaml>=6.0
Requires-Dist: radon>=6.0.0
Provides-Extra: dev
Requires-Dist: black>=23.0.0; extra == 'dev'
Requires-Dist: mypy>=1.7.0; extra == 'dev'
Requires-Dist: pytest-cov>=4.1.0; extra == 'dev'
Requires-Dist: pytest>=7.4.0; extra == 'dev'
Requires-Dist: ruff>=0.1.0; extra == 'dev'
Requires-Dist: types-pyyaml>=6.0; extra == 'dev'
